setup.cfg
setup.py
src/algebraic/__init__.py
src/algebraic/expression.py
src/algebraic/variable.py
src/python_algebraic.egg-info/PKG-INFO
src/python_algebraic.egg-info/SOURCES.txt
src/python_algebraic.egg-info/dependency_links.txt
src/python_algebraic.egg-info/top_level.txt
src/python_algebraic.egg-info/zip-safe