Metadata-Version: 1.0
Name: python-algebraic
Version: 0.3.1.dev-20120112
Summary: Algebraic modeling system for Python
Home-page: https://github.com/rzoz/python-algebraic
Author: Ryan J. O'Neil
Author-email: ryanjoneil@gmail.com
License: UNKNOWN
Keywords: algebraic modeling model modeler
Platform: UNKNOWN
Classifier: Development Status :: 4 - Beta
Classifier: Intended Audience :: Science/Research
Classifier: License :: OSI Approved :: BSD License
Classifier: Programming Language :: Python
Classifier: Topic :: Scientific/Engineering :: Mathematics
